<?xml version="1.0" standalone="yes"?>
<HS_Elements xmlns="http://tempuri.org/HS_Elements.xsd">
  <Channels>
    <_lab>FT0102</_lab>
    <_prompt>06_Ch4</_prompt>
    <_summary>热边入口流量</_summary>
    <_type>Feedback</_type>
    <_sensor>FT0102</_sensor>
  </Channels>
  <Channels>
    <_lab>PT0104</_lab>
    <_prompt>03_Ch1</_prompt>
    <_summary>热边电炉入口空气压力</_summary>
    <_type>Measure</_type>
    <_sensor>PT0104</_sensor>
  </Channels>
  <Channels>
    <_lab>TT0102</_lab>
    <_prompt>01_Ch2</_prompt>
    <_summary>热边电炉入口空气温度</_summary>
    <_type>Measure</_type>
    <_sensor>TT0102</_sensor>
  </Channels>
  <Channels>
    <_lab>PT0106</_lab>
    <_prompt>03_Ch2</_prompt>
    <_summary>热边电炉出口空气压力</_summary>
    <_type>Measure</_type>
    <_sensor>PT0106</_sensor>
  </Channels>
  <Channels>
    <_lab>TT0104</_lab>
    <_prompt>02_Ch4</_prompt>
    <_summary>热边电炉出口空气温度</_summary>
    <_type>Measure</_type>
    <_sensor>TT0104</_sensor>
  </Channels>
  <Channels>
    <_lab>PT0108</_lab>
    <_prompt>03_Ch3</_prompt>
    <_summary>热边实验段入口空气压力</_summary>
    <_type>Measure</_type>
    <_sensor>PT0108</_sensor>
  </Channels>
  <Channels>
    <_lab>TT0106</_lab>
    <_prompt>02_Ch5</_prompt>
    <_summary>热边实验段入口空气温度</_summary>
    <_type>Feedback</_type>
    <_sensor>TT0106</_sensor>
  </Channels>
  <Channels>
    <_lab>PT0109</_lab>
    <_prompt>03_Ch4</_prompt>
    <_summary>热边实验段出口空气压力</_summary>
    <_type>Measure</_type>
    <_sensor>PT0109</_sensor>
  </Channels>
  <Channels>
    <_lab>TT0107</_lab>
    <_prompt>02_Ch6</_prompt>
    <_summary>热边实验段出口空气温度</_summary>
    <_type>Measure</_type>
    <_sensor>TT0107</_sensor>
  </Channels>
  <Channels>
    <_lab>FT0101</_lab>
    <_prompt>06_Ch3</_prompt>
    <_summary>二冷入口空气流量</_summary>
    <_type>Feedback</_type>
    <_sensor>FT0101</_sensor>
  </Channels>
  <Channels>
    <_lab>PT0103</_lab>
    <_prompt>01_Ch6</_prompt>
    <_summary>二冷电炉入口空气压力</_summary>
    <_type>Measure</_type>
    <_sensor>PT0103</_sensor>
  </Channels>
  <Channels>
    <_lab>TT0101</_lab>
    <_prompt>01_Ch1</_prompt>
    <_summary>二冷电炉入口空气温度</_summary>
    <_type>Measure</_type>
    <_sensor>TT0101</_sensor>
  </Channels>
  <Channels>
    <_lab>PT0105</_lab>
    <_prompt>02_Ch1</_prompt>
    <_summary>二冷电炉出口空气压力</_summary>
    <_type>Measure</_type>
    <_sensor>PT0105</_sensor>
  </Channels>
  <Channels>
    <_lab>TT0103</_lab>
    <_prompt>01_Ch3</_prompt>
    <_summary>二冷电炉出口空气温度</_summary>
    <_type>Measure</_type>
    <_sensor>TT0103</_sensor>
  </Channels>
  <Channels>
    <_lab>PT0107</_lab>
    <_prompt>02_Ch2</_prompt>
    <_summary>二冷实验段入口空气压力</_summary>
    <_type>Measure</_type>
    <_sensor>PT0107</_sensor>
  </Channels>
  <Channels>
    <_lab>TT0105</_lab>
    <_prompt>01_Ch4</_prompt>
    <_summary>二冷实验段入口空气温度</_summary>
    <_type>Feedback</_type>
    <_sensor>TT0105</_sensor>
  </Channels>
  <Channels>
    <_lab>PT0110</_lab>
    <_prompt>02_Ch3</_prompt>
    <_summary>二冷实验段出口空气压力</_summary>
    <_type>Measure</_type>
    <_sensor>PT0110</_sensor>
  </Channels>
  <Channels>
    <_lab>TT0108</_lab>
    <_prompt>01_Ch5</_prompt>
    <_summary>二冷实验段出口空气温度</_summary>
    <_type>Measure</_type>
    <_sensor>TT0108</_sensor>
  </Channels>
  <Channels>
    <_lab>FT0103</_lab>
    <_prompt>06_Ch5</_prompt>
    <_summary>一冷入口空气流量</_summary>
    <_type>Feedback</_type>
    <_sensor>FT0103</_sensor>
  </Channels>
  <Channels>
    <_lab>PT01</_lab>
    <_prompt>05_Ch1</_prompt>
    <_summary>一冷入口空气压力</_summary>
    <_type>Measure</_type>
    <_sensor>PT01</_sensor>
  </Channels>
  <Channels>
    <_lab>TT01</_lab>
    <_prompt>03_Ch5</_prompt>
    <_summary>一冷入口空气温度</_summary>
    <_type>Measure</_type>
    <_sensor>TT01</_sensor>
  </Channels>
  <Channels>
    <_lab>PT02</_lab>
    <_prompt>05_Ch2</_prompt>
    <_summary>一冷入口空气压力</_summary>
    <_type>Measure</_type>
    <_sensor>PT02</_sensor>
  </Channels>
  <Channels>
    <_lab>TT02</_lab>
    <_prompt>03_Ch6</_prompt>
    <_summary>一冷入口空气温度</_summary>
    <_type>Measure</_type>
    <_sensor>TT02</_sensor>
  </Channels>
  <Channels>
    <_lab>PT03</_lab>
    <_prompt>05_Ch3</_prompt>
    <_summary>一冷出口空气压力</_summary>
    <_type>Measure</_type>
    <_sensor>PT03</_sensor>
  </Channels>
  <Channels>
    <_lab>TT03</_lab>
    <_prompt>04_Ch1</_prompt>
    <_summary>一冷出口空气温度</_summary>
    <_type>Measure</_type>
    <_sensor>TT03</_sensor>
  </Channels>
  <Channels>
    <_lab>PT04</_lab>
    <_prompt>05_Ch4</_prompt>
    <_summary>一冷出口空气压力</_summary>
    <_type>Measure</_type>
    <_sensor>PT04</_sensor>
  </Channels>
  <Channels>
    <_lab>TT04</_lab>
    <_prompt>04_Ch2</_prompt>
    <_summary>一冷出口空气温度</_summary>
    <_type>Measure</_type>
    <_sensor>TT04</_sensor>
  </Channels>
  <Channels>
    <_lab>PT05</_lab>
    <_prompt>05_Ch5</_prompt>
    <_summary>一冷出口空气压力</_summary>
    <_type>Measure</_type>
    <_sensor>PT05</_sensor>
  </Channels>
  <Channels>
    <_lab>TT05</_lab>
    <_prompt>04_Ch3</_prompt>
    <_summary>一冷出口空气温度</_summary>
    <_type>Measure</_type>
    <_sensor>TT05</_sensor>
  </Channels>
  <Channels>
    <_lab>PT06</_lab>
    <_prompt>05_Ch6</_prompt>
    <_summary>一冷出口空气压力</_summary>
    <_type>Measure</_type>
    <_sensor>PT06</_sensor>
  </Channels>
  <Channels>
    <_lab>TT06</_lab>
    <_prompt>04_Ch4</_prompt>
    <_summary>一冷出口空气温度</_summary>
    <_type>Measure</_type>
    <_sensor>TT06</_sensor>
  </Channels>
  <Channels>
    <_lab>PT07</_lab>
    <_prompt>06_Ch1</_prompt>
    <_summary>一冷出口空气压力</_summary>
    <_type>Measure</_type>
    <_sensor>PT07</_sensor>
  </Channels>
  <Channels>
    <_lab>TT07</_lab>
    <_prompt>04_Ch5</_prompt>
    <_summary>一冷出口空气温度</_summary>
    <_type>Measure</_type>
    <_sensor>TT07</_sensor>
  </Channels>
  <Channels>
    <_lab>PT08</_lab>
    <_prompt>06_Ch2</_prompt>
    <_summary>一冷出口空气压力</_summary>
    <_type>Measure</_type>
    <_sensor>PT08</_sensor>
  </Channels>
  <Channels>
    <_lab>TT08</_lab>
    <_prompt>04_Ch6</_prompt>
    <_summary>一冷出口空气温度</_summary>
    <_type>Measure</_type>
    <_sensor>TT08</_sensor>
  </Channels>
  <Sensors>
    <_lab>FT0102</_lab>
    <_sensorNumber>FT0102 000001</_sensorNumber>
    <_unit>Kg/h</_unit>
    <_elecRangeLow>4</_elecRangeLow>
    <_elecRangeHigh>20</_elecRangeHigh>
    <_qRangeLow>0</_qRangeLow>
    <_qRangeHigh>3200</_qRangeHigh>
  </Sensors>
  <Sensors>
    <_lab>PT0104</_lab>
    <_sensorNumber>PT0104 000001</_sensorNumber>
    <_unit>KPa</_unit>
    <_elecRangeLow>4</_elecRangeLow>
    <_elecRangeHigh>20</_elecRangeHigh>
    <_qRangeLow>0</_qRangeLow>
    <_qRangeHigh>2500</_qRangeHigh>
  </Sensors>
  <Sensors>
    <_lab>TT0102</_lab>
    <_sensorNumber>TT0102 000001</_sensorNumber>
    <_unit>℃</_unit>
    <_elecRangeLow>4</_elecRangeLow>
    <_elecRangeHigh>20</_elecRangeHigh>
    <_qRangeLow>0</_qRangeLow>
    <_qRangeHigh>150</_qRangeHigh>
  </Sensors>
  <Sensors>
    <_lab>PT0106</_lab>
    <_sensorNumber>PT0104 000001</_sensorNumber>
    <_unit>KPa</_unit>
    <_elecRangeLow>4</_elecRangeLow>
    <_elecRangeHigh>20</_elecRangeHigh>
    <_qRangeLow>0</_qRangeLow>
    <_qRangeHigh>2500</_qRangeHigh>
  </Sensors>
  <Sensors>
    <_lab>TT0104</_lab>
    <_sensorNumber>TT0104 000001</_sensorNumber>
    <_unit>℃</_unit>
    <_elecRangeLow>4</_elecRangeLow>
    <_elecRangeHigh>20</_elecRangeHigh>
    <_qRangeLow>0</_qRangeLow>
    <_qRangeHigh>750</_qRangeHigh>
  </Sensors>
  <Sensors>
    <_lab>PT0108</_lab>
    <_sensorNumber>PT0108 000001</_sensorNumber>
    <_unit>KPa</_unit>
    <_elecRangeLow>4</_elecRangeLow>
    <_elecRangeHigh>20</_elecRangeHigh>
    <_qRangeLow>0</_qRangeLow>
    <_qRangeHigh>2500</_qRangeHigh>
  </Sensors>
  <Sensors>
    <_lab>TT0106</_lab>
    <_sensorNumber>TT0106 000001</_sensorNumber>
    <_unit>℃</_unit>
    <_elecRangeLow>4</_elecRangeLow>
    <_elecRangeHigh>20</_elecRangeHigh>
    <_qRangeLow>0</_qRangeLow>
    <_qRangeHigh>750</_qRangeHigh>
  </Sensors>
  <Sensors>
    <_lab>PT0109</_lab>
    <_sensorNumber>PT0109 000001</_sensorNumber>
    <_unit>KPa</_unit>
    <_elecRangeLow>4</_elecRangeLow>
    <_elecRangeHigh>20</_elecRangeHigh>
    <_qRangeLow>0</_qRangeLow>
    <_qRangeHigh>2500</_qRangeHigh>
  </Sensors>
  <Sensors>
    <_lab>TT0107</_lab>
    <_sensorNumber>TT0107 000001</_sensorNumber>
    <_unit>℃</_unit>
    <_elecRangeLow>4</_elecRangeLow>
    <_elecRangeHigh>20</_elecRangeHigh>
    <_qRangeLow>0</_qRangeLow>
    <_qRangeHigh>750</_qRangeHigh>
  </Sensors>
  <Sensors>
    <_lab>FT0101</_lab>
    <_sensorNumber>FT0102 000001</_sensorNumber>
    <_unit>Kg/h</_unit>
    <_elecRangeLow>4</_elecRangeLow>
    <_elecRangeHigh>20</_elecRangeHigh>
    <_qRangeLow>0</_qRangeLow>
    <_qRangeHigh>6200</_qRangeHigh>
  </Sensors>
  <Sensors>
    <_lab>PT0103</_lab>
    <_sensorNumber>PT0103 000001</_sensorNumber>
    <_unit>KPa</_unit>
    <_elecRangeLow>4</_elecRangeLow>
    <_elecRangeHigh>20</_elecRangeHigh>
    <_qRangeLow>0</_qRangeLow>
    <_qRangeHigh>1000</_qRangeHigh>
  </Sensors>
  <Sensors>
    <_lab>TT0101</_lab>
    <_sensorNumber>TT0101 000001</_sensorNumber>
    <_unit>℃</_unit>
    <_elecRangeLow>4</_elecRangeLow>
    <_elecRangeHigh>20</_elecRangeHigh>
    <_qRangeLow>0</_qRangeLow>
    <_qRangeHigh>100</_qRangeHigh>
  </Sensors>
  <Sensors>
    <_lab>PT0105</_lab>
    <_sensorNumber>PT0105 000001</_sensorNumber>
    <_unit>KPa</_unit>
    <_elecRangeLow>4</_elecRangeLow>
    <_elecRangeHigh>20</_elecRangeHigh>
    <_qRangeLow>0</_qRangeLow>
    <_qRangeHigh>1000</_qRangeHigh>
  </Sensors>
  <Sensors>
    <_lab>TT0103</_lab>
    <_sensorNumber>TT0103 000001</_sensorNumber>
    <_unit>℃</_unit>
    <_elecRangeLow>4</_elecRangeLow>
    <_elecRangeHigh>20</_elecRangeHigh>
    <_qRangeLow>0</_qRangeLow>
    <_qRangeHigh>150</_qRangeHigh>
  </Sensors>
  <Sensors>
    <_lab>PT0107</_lab>
    <_sensorNumber>PT0107 000001</_sensorNumber>
    <_unit>KPa</_unit>
    <_elecRangeLow>4</_elecRangeLow>
    <_elecRangeHigh>20</_elecRangeHigh>
    <_qRangeLow>0</_qRangeLow>
    <_qRangeHigh>1000</_qRangeHigh>
  </Sensors>
  <Sensors>
    <_lab>TT0105</_lab>
    <_sensorNumber>TT0105 000001</_sensorNumber>
    <_unit>℃</_unit>
    <_elecRangeLow>4</_elecRangeLow>
    <_elecRangeHigh>20</_elecRangeHigh>
    <_qRangeLow>0</_qRangeLow>
    <_qRangeHigh>150</_qRangeHigh>
  </Sensors>
  <Sensors>
    <_lab>PT0110</_lab>
    <_sensorNumber>PT0110 000001</_sensorNumber>
    <_unit>KPa</_unit>
    <_elecRangeLow>4</_elecRangeLow>
    <_elecRangeHigh>20</_elecRangeHigh>
    <_qRangeLow>0</_qRangeLow>
    <_qRangeHigh>1000</_qRangeHigh>
  </Sensors>
  <Sensors>
    <_lab>TT0108</_lab>
    <_sensorNumber>TT0108 000001</_sensorNumber>
    <_unit>℃</_unit>
    <_elecRangeLow>4</_elecRangeLow>
    <_elecRangeHigh>20</_elecRangeHigh>
    <_qRangeLow>0</_qRangeLow>
    <_qRangeHigh>150</_qRangeHigh>
  </Sensors>
  <Sensors>
    <_lab>FT0103</_lab>
    <_sensorNumber>FT0103 000001</_sensorNumber>
    <_unit>Kg/h</_unit>
    <_elecRangeLow>4</_elecRangeLow>
    <_elecRangeHigh>20</_elecRangeHigh>
    <_qRangeLow>0</_qRangeLow>
    <_qRangeHigh>33000</_qRangeHigh>
  </Sensors>
  <Sensors>
    <_lab>PT01</_lab>
    <_sensorNumber>PT01 000001</_sensorNumber>
    <_unit>KPa</_unit>
    <_elecRangeLow>4</_elecRangeLow>
    <_elecRangeHigh>20</_elecRangeHigh>
    <_qRangeLow>0</_qRangeLow>
    <_qRangeHigh>150</_qRangeHigh>
  </Sensors>
  <Sensors>
    <_lab>TT01</_lab>
    <_sensorNumber>TT01 000001</_sensorNumber>
    <_unit>℃</_unit>
    <_elecRangeLow>4</_elecRangeLow>
    <_elecRangeHigh>20</_elecRangeHigh>
    <_qRangeLow>0</_qRangeLow>
    <_qRangeHigh>100</_qRangeHigh>
  </Sensors>
  <Sensors>
    <_lab>PT02</_lab>
    <_sensorNumber>PT02 000001</_sensorNumber>
    <_unit>KPa</_unit>
    <_elecRangeLow>4</_elecRangeLow>
    <_elecRangeHigh>20</_elecRangeHigh>
    <_qRangeLow>0</_qRangeLow>
    <_qRangeHigh>150</_qRangeHigh>
  </Sensors>
  <Sensors>
    <_lab>TT02</_lab>
    <_sensorNumber>TT02 000001</_sensorNumber>
    <_unit>℃</_unit>
    <_elecRangeLow>4</_elecRangeLow>
    <_elecRangeHigh>20</_elecRangeHigh>
    <_qRangeLow>0</_qRangeLow>
    <_qRangeHigh>100</_qRangeHigh>
  </Sensors>
  <Sensors>
    <_lab>PT03</_lab>
    <_sensorNumber>PT03 000001</_sensorNumber>
    <_unit>KPa</_unit>
    <_elecRangeLow>4</_elecRangeLow>
    <_elecRangeHigh>20</_elecRangeHigh>
    <_qRangeLow>0</_qRangeLow>
    <_qRangeHigh>150</_qRangeHigh>
  </Sensors>
  <Sensors>
    <_lab>TT03</_lab>
    <_sensorNumber>TT03 000001</_sensorNumber>
    <_unit>℃</_unit>
    <_elecRangeLow>4</_elecRangeLow>
    <_elecRangeHigh>20</_elecRangeHigh>
    <_qRangeLow>0</_qRangeLow>
    <_qRangeHigh>100</_qRangeHigh>
  </Sensors>
  <Sensors>
    <_lab>PT04</_lab>
    <_sensorNumber>PT04 000001</_sensorNumber>
    <_unit>KPa</_unit>
    <_elecRangeLow>4</_elecRangeLow>
    <_elecRangeHigh>20</_elecRangeHigh>
    <_qRangeLow>0</_qRangeLow>
    <_qRangeHigh>150</_qRangeHigh>
  </Sensors>
  <Sensors>
    <_lab>TT04</_lab>
    <_sensorNumber>TT04 000001</_sensorNumber>
    <_unit>℃</_unit>
    <_elecRangeLow>4</_elecRangeLow>
    <_elecRangeHigh>20</_elecRangeHigh>
    <_qRangeLow>0</_qRangeLow>
    <_qRangeHigh>100</_qRangeHigh>
  </Sensors>
  <Sensors>
    <_lab>PT05</_lab>
    <_sensorNumber>PT05 000001</_sensorNumber>
    <_unit>KPa</_unit>
    <_elecRangeLow>4</_elecRangeLow>
    <_elecRangeHigh>20</_elecRangeHigh>
    <_qRangeLow>0</_qRangeLow>
    <_qRangeHigh>150</_qRangeHigh>
  </Sensors>
  <Sensors>
    <_lab>TT05</_lab>
    <_sensorNumber>TT05 000001</_sensorNumber>
    <_unit>℃</_unit>
    <_elecRangeLow>4</_elecRangeLow>
    <_elecRangeHigh>20</_elecRangeHigh>
    <_qRangeLow>0</_qRangeLow>
    <_qRangeHigh>100</_qRangeHigh>
  </Sensors>
  <Sensors>
    <_lab>PT06</_lab>
    <_sensorNumber>PT06 000001</_sensorNumber>
    <_unit>KPa</_unit>
    <_elecRangeLow>4</_elecRangeLow>
    <_elecRangeHigh>20</_elecRangeHigh>
    <_qRangeLow>0</_qRangeLow>
    <_qRangeHigh>150</_qRangeHigh>
  </Sensors>
  <Sensors>
    <_lab>TT06</_lab>
    <_sensorNumber>TT06 000001</_sensorNumber>
    <_unit>℃</_unit>
    <_elecRangeLow>4</_elecRangeLow>
    <_elecRangeHigh>20</_elecRangeHigh>
    <_qRangeLow>0</_qRangeLow>
    <_qRangeHigh>100</_qRangeHigh>
  </Sensors>
  <Sensors>
    <_lab>PT07</_lab>
    <_sensorNumber>PT07 000001</_sensorNumber>
    <_unit>KPa</_unit>
    <_elecRangeLow>4</_elecRangeLow>
    <_elecRangeHigh>20</_elecRangeHigh>
    <_qRangeLow>0</_qRangeLow>
    <_qRangeHigh>150</_qRangeHigh>
  </Sensors>
  <Sensors>
    <_lab>TT07</_lab>
    <_sensorNumber>TT03 000001</_sensorNumber>
    <_unit>℃</_unit>
    <_elecRangeLow>4</_elecRangeLow>
    <_elecRangeHigh>20</_elecRangeHigh>
    <_qRangeLow>0</_qRangeLow>
    <_qRangeHigh>100</_qRangeHigh>
  </Sensors>
  <Sensors>
    <_lab>PT08</_lab>
    <_sensorNumber>PT03 000001</_sensorNumber>
    <_unit>KPa</_unit>
    <_elecRangeLow>4</_elecRangeLow>
    <_elecRangeHigh>20</_elecRangeHigh>
    <_qRangeLow>0</_qRangeLow>
    <_qRangeHigh>150</_qRangeHigh>
  </Sensors>
  <Sensors>
    <_lab>TT08</_lab>
    <_sensorNumber>TT08 000001</_sensorNumber>
    <_unit>℃</_unit>
    <_elecRangeLow>4</_elecRangeLow>
    <_elecRangeHigh>20</_elecRangeHigh>
    <_qRangeLow>0</_qRangeLow>
    <_qRangeHigh>100</_qRangeHigh>
  </Sensors>
</HS_Elements>